[
    {
      "datestamp": "2021-09-20 01:06:38",
      "userid": 968,
      "lastmod": "2021-09-20 01:06:38",
      "refereed": "TRUE",
      "uri": "http:\/\/repository.lppm.unila.ac.id\/id\/eprint\/33973",
      "full_text_status": "public",
      "documents": [
          {
            "security": "public",
            "placement": 1,
            "eprintid": 33973,
            "mime_type": "application\/pdf",
            "language": "en",
            "files": [
                {
                  "objectid": 154221,
                  "uri": "http:\/\/repository.lppm.unila.ac.id\/id\/file\/401386",
                  "mime_type": "application\/pdf",
                  "fileid": 401386,
                  "hash": "edc37f54bd0f2faf22a82cca75d4e1d0",
                  "filename": "Buku Pendidikan Inklusif (Konsep & implementasi).pdf",
                  "hash_type": "MD5",
                  "mtime": "2021-09-19 13:44:21",
                  "datasetid": "document",
                  "filesize": 762695
                }
            ],
            "docid": 154221,
            "main": "Buku Pendidikan Inklusif (Konsep & implementasi).pdf",
            "rev_number": 1,
            "uri": "http:\/\/repository.lppm.unila.ac.id\/id\/document\/154221",
            "format": "text",
            "pos": 1
          }
      ],
      "publisher": "Graha Ilmu",
      "ispublished": "pub",
      "divisions": [
        "FKIP5"
      ],
      "type": "book",
      "editors": [
        {
          "name": {
            "lineage": null,
            "family": "Sowiyah",
            "honourific": null,
            "given": "Sowiyah"
          }
        }
      ],
      "pages": 122,
      "dir": "disk0\/00\/03\/39\/73",
      "date": 2019,
      "subjects": [
        "L1"
      ],
      "related_url": [
        {
          "type": "pub"
        }
      ],
      "status_changed": "2021-09-20 01:06:38",
      "eprint_status": "archive",
      "metadata_visibility": "show",
      "rev_number": 7,
      "title": "Pendidikan Inklusif (Konsep & Implementasi)",
      "date_type": "published",
      "isbn": "978-623-228-021-2",
      "eprintid": 33973
    },
    {
      "title": "Pengaruh Pembiayaan Pendidikan, Sarana Prasarana, dan Kompetensi Profesional Guru terhadap Mutu Sekolah Dasar",
      "rev_number": 7,
      "metadata_visibility": "show",
      "eprint_status": "archive",
      "status_changed": "2021-04-30 01:14:27",
      "subjects": [
        "L1"
      ],
      "thesis_type": "masters",
      "institution": "Universitas Lampung",
      "eprintid": 29793,
      "department": "MAP",
      "date_type": "completed",
      "ispublished": "unpub",
      "documents": [
          {
            "mime_type": "application\/pdf",
            "language": "en",
            "placement": 1,
            "security": "public",
            "eprintid": 29793,
            "uri": "http:\/\/repository.lppm.unila.ac.id\/id\/document\/43996",
            "rev_number": 1,
            "pos": 1,
            "format": "text",
            "files": [
                {
                  "hash": "7145b8adc664c4ff84e86395719577d8",
                  "filename": "11 Tri Ardila.pdf",
                  "hash_type": "MD5",
                  "mtime": "2021-04-29 10:47:38",
                  "mime_type": "application\/pdf",
                  "fileid": 263625,
                  "filesize": 502393,
                  "datasetid": "document",
                  "uri": "http:\/\/repository.lppm.unila.ac.id\/id\/file\/263625",
                  "objectid": 43996
                }
            ],
            "main": "11 Tri Ardila.pdf",
            "docid": 43996
          }
      ],
      "full_text_status": "public",
      "uri": "http:\/\/repository.lppm.unila.ac.id\/id\/eprint\/29793",
      "thesis_name": "other",
      "lastmod": "2021-04-30 01:14:27",
      "userid": 214,
      "datestamp": "2021-04-30 01:14:27",
      "creators": [
        {
          "name": {
            "given": "Tri",
            "lineage": null,
            "family": "Ardila",
            "honourific": null
          }
        }
      ],
      "date": 2019,
      "dir": "disk0\/00\/02\/97\/93",
      "type": "thesis",
      "divisions": [
        "FKIP5"
      ]
    },
    {
      "uri": "http:\/\/repository.lppm.unila.ac.id\/id\/eprint\/28835",
      "full_text_status": "public",
      "publisher": "JPP FKIP Universitas Lampung",
      "documents": [
          {
            "eprintid": 28835,
            "security": "public",
            "placement": 1,
            "mime_type": "application\/pdf",
            "language": "en",
            "docid": 42928,
            "main": "The Novel Work Environment Model to Improve Teacher Performance A Study at SMAN 1 Sungkai Jaya, North Lampung.pdf",
            "files": [
                {
                  "uri": "http:\/\/repository.lppm.unila.ac.id\/id\/file\/255860",
                  "objectid": 42928,
                  "filesize": 3173317,
                  "datasetid": "document",
                  "hash_type": "MD5",
                  "mtime": "2021-04-01 08:43:27",
                  "hash": "9547997fb45294f1eaa8d12e287b8cf8",
                  "filename": "The Novel Work Environment Model to Improve Teacher Performance A Study at SMAN 1 Sungkai Jaya, North Lampung.pdf",
                  "fileid": 255860,
                  "mime_type": "application\/pdf"
                }
            ],
            "format": "text",
            "pos": 1,
            "uri": "http:\/\/repository.lppm.unila.ac.id\/id\/document\/42928",
            "rev_number": 1
          }
      ],
      "ispublished": "pub",
      "datestamp": "2021-04-05 04:49:51",
      "lastmod": "2021-04-05 04:49:51",
      "userid": 214,
      "dir": "disk0\/00\/02\/88\/35",
      "date": "2019-11-01",
      "creators": [
        {
          "name": {
            "given": "Nitalinda",
            "honourific": null,
            "family": "Desy",
            "lineage": null
          },
          "id": null
        },
        {
          "id": "abdurrahman.1968@fkip.unila.ac.id",
          "name": {
            "family": "Abdurrahman",
            "honourific": null,
            "lineage": null,
            "given": "Abdurrahman"
          }
        },
        {
          "name": {
            "given": "Hasan",
            "family": "Hariri",
            "honourific": null,
            "lineage": null
          },
          "id": "hasan.hariri@staff.unila.ac.id"
        },
        {
          "id": null,
          "name": {
            "honourific": null,
            "family": "Sowiyah",
            "lineage": null,
            "given": "Sowiyah"
          }
        }
      ],
      "divisions": [
        "FKIP5"
      ],
      "type": "other",
      "metadata_visibility": "show",
      "rev_number": 9,
      "title": "The Novel Work Environment Model to Improve Teacher Performance: A Study at SMAN 1 Sungkai Jaya, North Lampung.",
      "subjects": [
        "L1",
        "LB1501",
        "LC5201"
      ],
      "status_changed": "2021-04-05 04:49:51",
      "eprint_status": "archive",
      "eprintid": 28835
    },
    {
      "eprintid": 33983,
      "date_type": "published",
      "related_url": [
        {
          "url": "http:\/\/jurnal.fkip.unila.ac.id\/index.php\/jpp\/",
          "type": "pub"
        }
      ],
      "status_changed": "2021-09-20 01:07:12",
      "eprint_status": "archive",
      "abstract": "This study aims to create a good\r\nenvironment in order to improve teacher performance in SMA Negeri 1 Sungkai Jaya, North Lampung.\r\nIn this study, a combination of two aspects of the work environment model was carried out to create\r\na reflective and appropriate work environment model. Methods: This study uses qualitative methods\r\nwith 50 respondents. Data collection techniques were carried out through observation, interviews,\r\ndocumentation, and Focus Group Discussions (FGD). Findings: The results showed that the social\r\nenvironment at SMAN 1 was good enough to produce good teacher outcomes, but improving\r\ncommunication caused discomfort between the teacher and school principal relations. The artistic\r\nenvironment at SMAN 1 shows that the teachers in carrying out the assignments given by the principal\r\nare going well, in an orderly and disciplined manner, but the quality of the learning tools is better than\r\nthe difficulties in time. Conclusions: Model The reflective work environment has a good status on\r\nthe relationship between the principal and the teacher because the teacher and the principal are not\r\ndirectly related.",
      "subjects": [
        "L1"
      ],
      "title": "The Novel Work Environment Model to Improve Teacher Performance:\r\nA Study at SMAN 1 Sungkai Jaya, North Lampung",
      "official_url": "http:\/\/jurnal.fkip.unila.ac.id\/index.php\/jpp\/",
      "metadata_visibility": "show",
      "volume": 9,
      "rev_number": 7,
      "type": "article",
      "divisions": [
        "FKIP5"
      ],
      "creators": [
        {
          "name": {
            "given": "Desy",
            "family": "Desy Nitalinda",
            "honourific": null,
            "lineage": null
          }
        },
        {
          "name": {
            "family": "Abdurrahman",
            "honourific": null,
            "lineage": null,
            "given": "Abdurrahman"
          }
        },
        {
          "name": {
            "lineage": null,
            "family": "Hasan",
            "honourific": null,
            "given": "Hariri"
          }
        },
        {
          "name": {
            "lineage": null,
            "family": "Sowiyah",
            "honourific": null,
            "given": "Sowiyah"
          }
        },
        {
          "name": {
            "given": "Dedy",
            "family": "Dedy hermanto Karwan",
            "honourific": null,
            "lineage": null
          }
        },
        {
          "name": {
            "honourific": null,
            "family": "Bujang Rahman",
            "lineage": null,
            "given": "Rahman"
          }
        }
      ],
      "issn": "e-ISSN: 2550-1313 | p-ISSN: 2087-9849",
      "publication": "Jurnal Pendidikan Progresif",
      "date": "2019-11-11",
      "dir": "disk0\/00\/03\/39\/83",
      "lastmod": "2021-09-20 01:07:12",
      "userid": 968,
      "pagerange": "54-62",
      "datestamp": "2021-09-20 01:07:12",
      "documents": [
          {
            "uri": "http:\/\/repository.lppm.unila.ac.id\/id\/document\/154231",
            "rev_number": 1,
            "format": "text",
            "pos": 1,
            "files": [
                {
                  "objectid": 154231,
                  "uri": "http:\/\/repository.lppm.unila.ac.id\/id\/file\/401450",
                  "datasetid": "document",
                  "filesize": 1864331,
                  "mime_type": "application\/pdf",
                  "fileid": 401450,
                  "filename": "2. Nitalinda et al inc Hariri 2019 The Novel Work Environment Model to Improve Teacher Performance.pdf",
                  "hash": "f81c21295d62bbc9d5cae53f8cbf5b7f",
                  "mtime": "2021-09-19 15:23:52",
                  "hash_type": "MD5"
                }
            ],
            "main": "2. Nitalinda et al inc Hariri 2019 The Novel Work Environment Model to Improve Teacher Performance.pdf",
            "docid": 154231,
            "language": "en",
            "mime_type": "application\/pdf",
            "security": "public",
            "placement": 1,
            "eprintid": 33983
          }
      ],
      "publisher": "FKIP Universitas Lampung",
      "number": 2,
      "ispublished": "pub",
      "refereed": "TRUE",
      "uri": "http:\/\/repository.lppm.unila.ac.id\/id\/eprint\/33983",
      "full_text_status": "public"
    },
    {
      "eprintid": 33985,
      "date_type": "published",
      "title": "The Correlation of The Skill Variations and Learning Interest with Learning Result of Class 5th",
      "official_url": "http:\/\/jurnal.fkip.unila.ac.id\/index.php\/pgsd\/article\/view\/18774",
      "metadata_visibility": "show",
      "volume": 7,
      "rev_number": 6,
      "related_url": [
        {
          "url": "http:\/\/jurnal.fkip.unila.ac.id\/index.php\/pgsd\/article\/view\/18774",
          "type": "pub"
        }
      ],
      "status_changed": "2021-09-20 01:07:17",
      "eprint_status": "archive",
      "abstract": "The purpose of the research was to analyze and to know the positive and significant correlation between the skill variations and learning interest with students learning result of class 5th at elementary school gugus cut nyak dien east metro distric. The Method used of this research is ex-postfacto correlational. The population are 195 students and the research sample are 64 students. The data collection used the techniques observation, quetionnaire, and study documentations. The result showed that there were positive and significant correlation between the skill variations and learning interest with students learning result of class 5th at elementary school gugus cut nyak dien east metro distric with coefficient correlation 0,568 marked positive with strong enough criteria.",
      "subjects": [
        "L1"
      ],
      "creators": [
        {
          "name": {
            "given": "Fitria",
            "honourific": null,
            "family": "Fitria Agustina",
            "lineage": null
          }
        },
        {
          "name": {
            "given": "Sowiyah",
            "lineage": null,
            "honourific": null,
            "family": "Sowiyah"
          }
        },
        {
          "name": {
            "given": "Siswantoro",
            "lineage": null,
            "honourific": null,
            "family": "Siswantoro"
          }
        }
      ],
      "publication": "Pedagogi : Jurnal Pendidikan Dasar",
      "dir": "disk0\/00\/03\/39\/85",
      "date": 2019,
      "type": "article",
      "divisions": [
        "FKIP5"
      ],
      "documents": [
          {
            "files": [
                {
                  "filesize": 427474,
                  "datasetid": "document",
                  "hash_type": "MD5",
                  "mtime": "2021-09-19 15:39:45",
                  "hash": "e59d44671caa77d0d62af8a8a5747221",
                  "filename": "5. 18653-42679-1-PB.pdf",
                  "fileid": 401463,
                  "mime_type": "application\/pdf",
                  "uri": "http:\/\/repository.lppm.unila.ac.id\/id\/file\/401463",
                  "objectid": 154233
                }
            ],
            "docid": 154233,
            "main": "5. 18653-42679-1-PB.pdf",
            "uri": "http:\/\/repository.lppm.unila.ac.id\/id\/document\/154233",
            "rev_number": 1,
            "pos": 1,
            "format": "text",
            "placement": 1,
            "security": "public",
            "eprintid": 33985,
            "mime_type": "application\/pdf",
            "language": "en"
          }
      ],
      "ispublished": "pub",
      "number": 8,
      "refereed": "TRUE",
      "full_text_status": "public",
      "uri": "http:\/\/repository.lppm.unila.ac.id\/id\/eprint\/33985",
      "userid": 968,
      "lastmod": "2021-09-20 01:07:17",
      "datestamp": "2021-09-20 01:07:17"
    },
    {
      "divisions": [
        "FKIP5"
      ],
      "type": "other",
      "date": 2019,
      "dir": "disk0\/00\/03\/00\/06",
      "creators": [
        {
          "name": {
            "given": "Hasan",
            "lineage": null,
            "family": "Hariri",
            "honourific": null
          },
          "id": "hasan.hariri@staff.unila.ac.id"
        }
      ],
      "datestamp": "2021-05-05 07:39:20",
      "lastmod": "2021-05-05 07:39:20",
      "userid": 214,
      "full_text_status": "public",
      "uri": "http:\/\/repository.lppm.unila.ac.id\/id\/eprint\/30006",
      "ispublished": "pub",
      "documents": [
          {
            "main": "1 Reviewer SAGE Open Juli 2019.pdf",
            "docid": 134672,
            "files": [
                {
                  "filename": "1 Reviewer SAGE Open Juli 2019.pdf",
                  "hash": "d676d38d6febc59b20fc67a11b55bb8d",
                  "hash_type": "MD5",
                  "mtime": "2021-05-05 07:11:24",
                  "mime_type": "application\/pdf",
                  "fileid": 355668,
                  "filesize": 99062,
                  "datasetid": "document",
                  "uri": "http:\/\/repository.lppm.unila.ac.id\/id\/file\/355668",
                  "objectid": 134672
                }
            ],
            "format": "text",
            "pos": 1,
            "uri": "http:\/\/repository.lppm.unila.ac.id\/id\/document\/134672",
            "rev_number": 1,
            "eprintid": 30006,
            "security": "public",
            "placement": 1,
            "language": "en",
            "mime_type": "application\/pdf"
          }
      ],
      "publisher": "SAGE open",
      "date_type": "completed",
      "eprintid": 30006,
      "subjects": [
        "L1"
      ],
      "abstract": "Menjadi reviewer pada jurnal internasional bereputasi SAGE Open: reviewing manuscript # SO-19-0339 entitled \"Principal Leadership Style and Teacher Job Performance: Evidence from Pakistan\" for SAGE Open (bukti: email dari SAGE Open terlampir tanggal 06-Jul-2019).",
      "status_changed": "2021-05-05 07:39:20",
      "eprint_status": "archive",
      "rev_number": 10,
      "metadata_visibility": "show",
      "title": "Reviewing manuscript # SO-19-0339 entitled \"Principal Leadership Style and Teacher Job Performance: Evidence from Pakistan\" for SAGE Open in July 2019"
    },
    {
      "full_text_status": "public",
      "uri": "http:\/\/repository.lppm.unila.ac.id\/id\/eprint\/30007",
      "ispublished": "pub",
      "publisher": "SAGE open",
      "documents": [
          {
            "eprintid": 30007,
            "security": "public",
            "placement": 1,
            "language": "en",
            "mime_type": "application\/pdf",
            "main": "2 Reviewer SAGE Open Desember 2019.pdf",
            "docid": 134674,
            "files": [
                {
                  "objectid": 134674,
                  "uri": "http:\/\/repository.lppm.unila.ac.id\/id\/file\/355675",
                  "datasetid": "document",
                  "filesize": 99699,
                  "fileid": 355675,
                  "mime_type": "application\/pdf",
                  "mtime": "2021-05-05 07:17:46",
                  "hash_type": "MD5",
                  "filename": "2 Reviewer SAGE Open Desember 2019.pdf",
                  "hash": "05f06003d6327cc4d542084c272204b3"
                }
            ],
            "format": "text",
            "pos": 1,
            "rev_number": 1,
            "uri": "http:\/\/repository.lppm.unila.ac.id\/id\/document\/134674"
          }
      ],
      "datestamp": "2021-05-05 07:39:22",
      "lastmod": "2021-05-05 07:39:22",
      "userid": 214,
      "dir": "disk0\/00\/03\/00\/07",
      "date": 2019,
      "creators": [
        {
          "name": {
            "given": "Hasan",
            "family": "Hariri",
            "honourific": null,
            "lineage": null
          },
          "id": "hasan.hariri@staff.unila.ac.id"
        }
      ],
      "divisions": [
        "FKIP5"
      ],
      "type": "other",
      "rev_number": 7,
      "metadata_visibility": "show",
      "title": "Reviewing manuscript # SO-19-3132 entitled \"The Relationship Between School Principals’ Paternalistic Leadership and Teachers’ Job Burnout: An Action Research*\" for SAGE Open on December 2019",
      "subjects": [
        "L1"
      ],
      "abstract": "Menjadi reviewer pada jurnal internasional bereputasi SAGE Open: reviewing manuscript # SO-19-3132 entitled \"The Relationship Between School Principals’ Paternalistic Leadership and Teachers’ Job Burnout: An Action Research*\" for SAGE Open (bukti: email dari SAGE Open terlampir tanggal 15-Dec-2019).",
      "eprint_status": "archive",
      "status_changed": "2021-05-05 07:39:22",
      "date_type": "completed",
      "eprintid": 30007
    },
    {
      "datestamp": "2021-05-05 01:03:25",
      "lastmod": "2021-05-05 01:03:25",
      "userid": 214,
      "uri": "http:\/\/repository.lppm.unila.ac.id\/id\/eprint\/29961",
      "thesis_name": "other",
      "full_text_status": "public",
      "documents": [
          {
            "mime_type": "application\/pdf",
            "language": "en",
            "eprintid": 29961,
            "placement": 1,
            "security": "public",
            "pos": 1,
            "format": "text",
            "rev_number": 1,
            "uri": "http:\/\/repository.lppm.unila.ac.id\/id\/document\/134434",
            "docid": 134434,
            "main": "17 Nurlaely Kholidah p2.pdf",
            "files": [
                {
                  "filesize": 226588,
                  "datasetid": "document",
                  "hash": "eefb06a123755e906c14181e97dc7504",
                  "filename": "17 Nurlaely Kholidah p2.pdf",
                  "mtime": "2021-05-04 14:34:00",
                  "hash_type": "MD5",
                  "mime_type": "application\/pdf",
                  "fileid": 355137,
                  "uri": "http:\/\/repository.lppm.unila.ac.id\/id\/file\/355137",
                  "objectid": 134434
                }
            ]
          }
      ],
      "ispublished": "unpub",
      "divisions": [
        "FKIP5"
      ],
      "type": "thesis",
      "dir": "disk0\/00\/02\/99\/61",
      "date": 2019,
      "creators": [
        {
          "name": {
            "given": "Nurlalely",
            "family": "Kholidah",
            "honourific": null,
            "lineage": null
          }
        }
      ],
      "subjects": [
        "L1"
      ],
      "eprint_status": "archive",
      "status_changed": "2021-05-05 01:03:25",
      "metadata_visibility": "show",
      "rev_number": 8,
      "title": "Manajemen Hubungan Sekolah dan Masyarakat di SMA Diniyyah Putri Lampung",
      "date_type": "completed",
      "department": "MAP",
      "eprintid": 29961,
      "institution": "Universitas Lampung",
      "thesis_type": "other"
    },
    {
      "lastmod": "2021-04-30 01:14:15",
      "userid": 214,
      "datestamp": "2021-04-30 01:14:15",
      "documents": [
          {
            "security": "public",
            "placement": 1,
            "eprintid": 29788,
            "mime_type": "application\/pdf",
            "language": "en",
            "files": [
                {
                  "uri": "http:\/\/repository.lppm.unila.ac.id\/id\/file\/263590",
                  "objectid": 43991,
                  "hash": "6a821227401496400f46ec828f4a6d9f",
                  "filename": "6 Tesis Lourena Fitri.pdf",
                  "mtime": "2021-04-29 10:34:40",
                  "hash_type": "MD5",
                  "mime_type": "application\/pdf",
                  "fileid": 263590,
                  "filesize": 258204,
                  "datasetid": "document"
                }
            ],
            "docid": 43991,
            "main": "6 Tesis Lourena Fitri.pdf",
            "uri": "http:\/\/repository.lppm.unila.ac.id\/id\/document\/43991",
            "rev_number": 1,
            "format": "text",
            "pos": 1
          }
      ],
      "ispublished": "unpub",
      "uri": "http:\/\/repository.lppm.unila.ac.id\/id\/eprint\/29788",
      "full_text_status": "public",
      "thesis_name": "other",
      "type": "thesis",
      "divisions": [
        "FKIP5"
      ],
      "creators": [
        {
          "name": {
            "lineage": null,
            "family": "May",
            "honourific": null,
            "given": "Lourena Fitri"
          }
        }
      ],
      "date": 2019,
      "dir": "disk0\/00\/02\/97\/88",
      "status_changed": "2021-04-30 01:14:15",
      "eprint_status": "archive",
      "subjects": [
        "L1"
      ],
      "title": "Pengaruh Keterampilan Manajerial Kepala Sekolah, Disiplin Kerja, dan Motivasi Berprestasi terhadap Kinerja Guru pada SMKN di Kota Bandar Lampung",
      "metadata_visibility": "show",
      "rev_number": 7,
      "eprintid": 29788,
      "date_type": "completed",
      "department": "MAP",
      "institution": "Universitas Lampung",
      "thesis_type": "masters"
    },
    {
      "userid": 214,
      "lastmod": "2020-06-30 03:47:36",
      "datestamp": "2020-06-30 03:47:36",
      "pagerange": "54-62",
      "number": 2,
      "ispublished": "pub",
      "publisher": "FKIP Unila",
      "documents": [
          {
            "security": "public",
            "placement": 1,
            "eprintid": 22881,
            "content": "published",
            "language": "en",
            "mime_type": "application\/pdf",
            "files": [
                {
                  "filesize": 1864331,
                  "datasetid": "document",
                  "filename": "Nitalinda et al inc Hariri 2019 The Novel Work Environment Model to Improve Teacher Performance.pdf",
                  "hash": "f81c21295d62bbc9d5cae53f8cbf5b7f",
                  "mtime": "2019-11-14 14:47:30",
                  "hash_type": "MD5",
                  "mime_type": "application\/pdf",
                  "fileid": 209960,
                  "uri": "http:\/\/repository.lppm.unila.ac.id\/id\/file\/209960",
                  "objectid": 36426
                }
            ],
            "docid": 36426,
            "main": "Nitalinda et al inc Hariri 2019 The Novel Work Environment Model to Improve Teacher Performance.pdf",
            "formatdesc": "Reflective work environment has a good status on the relationship between principals and teachers.",
            "uri": "http:\/\/repository.lppm.unila.ac.id\/id\/document\/36426",
            "rev_number": 4,
            "format": "text",
            "pos": 1
          },
          {
            "mime_type": "application\/xml",
            "language": "en",
            "content": "published",
            "eprintid": 22881,
            "placement": 2,
            "security": "public",
            "pos": 2,
            "format": "other",
            "rev_number": 4,
            "uri": "http:\/\/repository.lppm.unila.ac.id\/id\/document\/36428",
            "formatdesc": "Reflective work environment has a good status on the relationship between principals and teachers.",
            "docid": 36428,
            "main": 19832,
            "files": [
                {
                  "objectid": 36428,
                  "uri": "http:\/\/repository.lppm.unila.ac.id\/id\/file\/209989",
                  "mime_type": "application\/xml",
                  "fileid": 209989,
                  "hash": "4a9dfc8e3edc5acbd8b4e32f3a6fb9d3",
                  "filename": 19832,
                  "hash_type": "MD5",
                  "mtime": "2020-06-30 03:32:10",
                  "datasetid": "document",
                  "filesize": 36915
                }
            ]
          }
      ],
      "full_text_status": "public",
      "uri": "http:\/\/repository.lppm.unila.ac.id\/id\/eprint\/22881",
      "refereed": "TRUE",
      "type": "article",
      "divisions": [
        "FKIP5"
      ],
      "publication": "Jurnal Pendidikan Progresif (JPP)",
      "issn": "e-ISSN: 2550-1313 | p-ISSN: 2087-9849",
      "creators": [
        {
          "name": {
            "given": "Desy",
            "lineage": null,
            "honourific": null,
            "family": "Nitalinda"
          },
          "id": null
        },
        {
          "id": null,
          "name": {
            "lineage": null,
            "family": "Abdurrahman",
            "honourific": null,
            "given": "Abdurrahman"
          }
        },
        {
          "id": "hasan.hariri@staff.unila.ac.id",
          "name": {
            "honourific": null,
            "family": "Hariri",
            "lineage": null,
            "given": "Hasan"
          }
        },
        {
          "id": null,
          "name": {
            "given": "Sowiyah",
            "lineage": null,
            "family": "Sowiyah",
            "honourific": null
          }
        },
        {
          "id": null,
          "name": {
            "given": "Dedy Hermanto",
            "lineage": null,
            "honourific": null,
            "family": "Karwan"
          }
        },
        {
          "id": null,
          "name": {
            "family": "Rahman",
            "honourific": null,
            "lineage": null,
            "given": "Bujang"
          }
        }
      ],
      "dir": "disk0\/00\/02\/28\/81",
      "date": "2019-11-11",
      "id_number": "10.23960\/jpp.v9.i2.201906",
      "status_changed": "2020-06-30 03:47:36",
      "eprint_status": "archive",
      "succeeds": 16471,
      "subjects": [
        "L1"
      ],
      "abstract": "The Novel Work Environment Model to Improve Teacher Performance: A Study\r\nat SMAN 1 Sungkai Jaya, North Lampung. Objectives: This study aims to create a good\r\nenvironment in order to improve teacher performance in SMA Negeri 1 Sungkai Jaya, North LampungIn this study, a combination of two aspects of the work environment model was carried out to create\r\na reflective and appropriate work environment model. Methods: This study uses qualitative methods\r\nwith 50 respondents. Data collection techniques were carried out through observation, interviewsdocumentation, and Focus Group Discussions (FGD). Findings: The results showed that the sociaenvironment at SMAN 1 was good enough to produce good teacher outcomes, but improving\r\ncommunication caused discomfort between the teacher and school principal relations. The artistic\r\nenvironment at SMAN 1 shows that the teachers in carrying out the assignments given by the principaare going well, in an orderly and disciplined manner, but the quality of the learning tools is better than the difficulties in time. Conclusions: Model of The reflective work environment has a good status on the relationship between the principal and the teacher because the teacher and the principal are not directly related.\r\nKeywords: Reflective work environment model, school, teacher performance.",
      "official_url": "http:\/\/jurnal.fkip.unila.ac.id\/index.php\/jpp\/",
      "title": "The Novel Work Environment Model to Improve Teacher Performance:A Study at SMAN 1 Sungkai Jaya, North Lampung",
      "rev_number": 6,
      "volume": 9,
      "metadata_visibility": "show",
      "eprintid": 22881,
      "date_type": "published"
    },
    {
      "uri": "http:\/\/repository.lppm.unila.ac.id\/id\/eprint\/29789",
      "full_text_status": "public",
      "thesis_name": "other",
      "ispublished": "unpub",
      "documents": [
          {
            "mime_type": "application\/pdf",
            "language": "en",
            "eprintid": 29789,
            "placement": 1,
            "security": "public",
            "pos": 1,
            "format": "text",
            "uri": "http:\/\/repository.lppm.unila.ac.id\/id\/document\/43992",
            "rev_number": 1,
            "docid": 43992,
            "main": "7 Tesis Nizam Pahlepi.pdf",
            "files": [
                {
                  "objectid": 43992,
                  "uri": "http:\/\/repository.lppm.unila.ac.id\/id\/file\/263597",
                  "mime_type": "application\/pdf",
                  "fileid": 263597,
                  "hash": "d34df28443ed7f6836de06140c944bc6",
                  "filename": "7 Tesis Nizam Pahlepi.pdf",
                  "hash_type": "MD5",
                  "mtime": "2021-04-29 10:37:13",
                  "datasetid": "document",
                  "filesize": 369320
                }
            ]
          }
      ],
      "datestamp": "2021-04-30 01:14:18",
      "lastmod": "2021-04-30 01:14:18",
      "userid": 214,
      "date": 2019,
      "dir": "disk0\/00\/02\/97\/89",
      "creators": [
        {
          "name": {
            "lineage": null,
            "honourific": null,
            "family": "Pahlepi",
            "given": "Nizam"
          }
        }
      ],
      "divisions": [
        "FKIP5"
      ],
      "type": "thesis",
      "rev_number": 7,
      "metadata_visibility": "show",
      "title": "Pengaruh Kepemimpinan Kepala Madrasah, Pengembangan Profesi, dan Kepercayaan Diri terhadap Kinerja Guru di Madrasah Ibtidaiyah Negeri Kota Bandar Lampung",
      "subjects": [
        "L1"
      ],
      "status_changed": "2021-04-30 01:14:18",
      "eprint_status": "archive",
      "thesis_type": "masters",
      "institution": "Universitas Lampung",
      "department": "MAP",
      "date_type": "completed",
      "eprintid": 29789
    },
    {
      "issn": "2454-6186",
      "creators": [
        {
          "id": "normaindahpertiwi@gmail.com",
          "name": {
            "lineage": null,
            "family": "Pratiwi",
            "honourific": null,
            "given": "Norma Indah"
          }
        },
        {
          "name": {
            "given": "Irawan",
            "lineage": null,
            "family": "Suntoro",
            "honourific": null
          },
          "id": "irawan.suntoro@fkip.unila.ac.id"
        },
        {
          "name": {
            "family": "Karwan",
            "honourific": null,
            "lineage": null,
            "given": "Dedy H."
          },
          "id": "dhkarwan@yahoo.co.id"
        }
      ],
      "publication": "International Journal of Research and Innovation in Social Science (IJRISS)",
      "date": "2019-10",
      "dir": "disk0\/00\/02\/29\/80",
      "type": "article",
      "divisions": [
        "FKIP5"
      ],
      "publisher": "www.rsisinternational.org",
      "documents": [
          {
            "language": "en",
            "mime_type": "application\/pdf",
            "content": "published",
            "eprintid": 22980,
            "placement": 2,
            "security": "public",
            "pos": 2,
            "format": "text",
            "rev_number": 4,
            "uri": "http:\/\/repository.lppm.unila.ac.id\/id\/document\/36531",
            "docid": 36531,
            "main": "3 Karwan 2019 Management of Education ImplementationSystems.pdf",
            "files": [
                {
                  "uri": "http:\/\/repository.lppm.unila.ac.id\/id\/file\/210671",
                  "objectid": 36531,
                  "mtime": "2020-07-01 19:33:35",
                  "hash_type": "MD5",
                  "hash": "b9a11b175a0d97dce44930a4a4d841f7",
                  "filename": "3 Karwan 2019 Management of Education ImplementationSystems.pdf",
                  "fileid": 210671,
                  "mime_type": "application\/pdf",
                  "filesize": 327937,
                  "datasetid": "document"
                }
            ]
          }
      ],
      "ispublished": "pub",
      "number": 10,
      "refereed": "TRUE",
      "uri": "http:\/\/repository.lppm.unila.ac.id\/id\/eprint\/22980",
      "full_text_status": "public",
      "lastmod": "2020-07-02 02:14:52",
      "userid": 685,
      "datestamp": "2020-07-02 02:14:52",
      "pagerange": "591-595",
      "eprintid": 22980,
      "title": "Management of Education Implementation Systems in Special Development Institute of Class II Bandar Lampung",
      "metadata_visibility": "show",
      "rev_number": 9,
      "volume": 3,
      "succeeds": 17208,
      "eprint_status": "archive",
      "status_changed": "2020-07-02 02:14:52",
      "abstract": "The concept of fulfilling the right to get education and teaching for correctional students in the Special Child Guidance Institution is to carry out education and teaching as sufficient provisions to continue their lives in the community with other communities after completing the training period. The education provided also aims to provide basic abilities to students to develop their lives as individuals, community members, citizens, and members of humanity. The implementation of prison rights as foster citizens at the Institute for Special Development of Children requires supporting facilities and infrastructure. One of them is a place to implement the rights of tegineneng correctional students is one of the Special Child Development Institutions in the Bandar Lampung region and the only one in Lampung province, Bandar Lampung Special Class II Child Development Institution has a distinct advantage from the Other Child Special Coaching Institutions namely the Institute Special Development for Children in Bandar Lampung Class II prioritizes the issue of Education. The number of students of the Special Guidance Institute for Class II in Bandar Lampung is based on the number that is differentiated or classified according to the level of classes taken before being placed in the Special Guidance Institute for Children in Bandar Lampung. that the system is a whole that has parts arranged systematically, the parts are interrelated with one another, and care for the environmental context.",
      "subjects": [
        "L1"
      ]
    },
    {
      "datestamp": "2019-04-29 07:55:19",
      "lastmod": "2019-04-29 07:55:19",
      "number": 1,
      "ispublished": "pub",
      "publisher": "IOP Publishing",
      "divisions": [
        "FKIP5"
      ],
      "type": "article",
      "date": "2019-02",
      "subjects": [
        "L1"
      ],
      "abstract": "The roles and responsibilities of schools in dealing with 21st-century problems, especially those related to global climate change which treats the entire world, become a challenge for school communities to take part to overcome this problem we proposed Green School Based Management Model (Green SBM Model). Green SBM Model is a new model that has been proposed to be conducted in all schools in Lampung. Just because the existed SBM Model focused on school improvement plans\/ learning outcomes only (management of human resources, materials, finance, strategic planning, program management, and marketing oriented). Before conducting Green SBM Model, we do need assessment surve for the teacher in Lampung Indonesia to know teacher perception about global warming and its solution. The design of this study is a cross-sectional non-experimental descriptive survey approach using a questionnaire to 107 teachers in Lampung, Indonesia. Based on data analysis, it can be concluded that all of the teachers realized the negative impact of global warming and they should take a part in overcoming the negative impact of global warming. Besides that, teachers also believed that Green School Based Management Model is a powerful model which can be a solution to overcome the negative impact of global warming",
      "eprint_status": "archive",
      "succeeds": 9179,
      "event_type": "conference",
      "official_url": "https:\/\/iopscience.iop.org\/article\/10.1088\/1742-6596\/1155\/1\/012086",
      "date_type": "published",
      "event_title": "YOUNG SCHOLAR SYMPOSIUM ON TRANSDISCIPLINARY IN EDUCATION AND ENVIRONMENT 2018",
      "eprintid": 11131,
      "pagerange": "1-6",
      "userid": 435,
      "uri": "http:\/\/repository.lppm.unila.ac.id\/id\/eprint\/11131",
      "full_text_status": "public",
      "refereed": "TRUE",
      "documents": [
          {
            "files": [
                {
                  "fileid": 101723,
                  "mime_type": "application\/vnd.openxmlformats-officedocument.wordprocessingml.document",
                  "hash_type": "MD5",
                  "mtime": "2018-10-31 10:18:44",
                  "hash": "cdf7e6cec81c5248a2b35059771a82f4",
                  "filename": "green school-rahmanB.docx",
                  "datasetid": "document",
                  "filesize": 34936,
                  "objectid": 24124,
                  "uri": "http:\/\/repository.lppm.unila.ac.id\/id\/file\/101723"
                }
            ],
            "docid": 24124,
            "main": "green school-rahmanB.docx",
            "uri": "http:\/\/repository.lppm.unila.ac.id\/id\/document\/24124",
            "rev_number": 2,
            "pos": 1,
            "format": "text",
            "placement": 1,
            "security": "public",
            "eprintid": 11131,
            "mime_type": "application\/vnd.openxmlformats-officedocument.wordprocessingml.document",
            "language": "en"
          },
          {
            "security": "public",
            "placement": 2,
            "eprintid": 11131,
            "language": "en",
            "mime_type": "application\/pdf",
            "files": [
                {
                  "datasetid": "document",
                  "filesize": 847812,
                  "mime_type": "application\/pdf",
                  "fileid": 101931,
                  "filename": "16.  Rahman_2019_J._Phys.__Conf._Ser._1155_012086.pdf",
                  "hash": "b15a30c05ee925edd1b38f4d4e250ab9",
                  "hash_type": "MD5",
                  "mtime": "2019-04-15 06:45:35",
                  "objectid": 24153,
                  "uri": "http:\/\/repository.lppm.unila.ac.id\/id\/file\/101931"
                }
            ],
            "main": "16.  Rahman_2019_J._Phys.__Conf._Ser._1155_012086.pdf",
            "docid": 24153,
            "uri": "http:\/\/repository.lppm.unila.ac.id\/id\/document\/24153",
            "rev_number": 1,
            "format": "text",
            "pos": 2
          }
      ],
      "pres_type": "paper",
      "dir": "disk0\/00\/01\/11\/31",
      "publication": "Journal of Physics: Conference Series",
      "issn": "Print : 1742-6588 Online : 1742-6596",
      "creators": [
        {
          "id": "bujang.suropati@gmail.com",
          "name": {
            "given": "Bujang",
            "family": "Rahman",
            "honourific": null,
            "lineage": null
          }
        },
        {
          "id": "abdurrahman.1968@fkip.unila.ac.id",
          "name": {
            "given": "Abdurrahman",
            "honourific": null,
            "family": "Abdurrahman",
            "lineage": null
          }
        },
        {
          "name": {
            "lineage": null,
            "family": "Riswandi",
            "honourific": null,
            "given": "riswandi"
          },
          "id": "riswandi.unila@gmail.com"
        },
        {
          "name": {
            "family": "Maulina",
            "honourific": null,
            "lineage": null,
            "given": "Hervin"
          },
          "id": "hervin.maulina@staff.unila.ac.id"
        }
      ],
      "status_changed": "2019-04-29 07:55:19",
      "rev_number": 8,
      "volume": 1155,
      "metadata_visibility": "show",
      "title": "Green School Based Management Model as A Powerfull Alternative Solution to Overcome Global Climate Change: A Need  Assesement Survey Analysis of Teacher in Lampung, Indonesia"
    },
    {
      "thesis_type": "masters",
      "institution": "Universitas Lampung",
      "eprintid": 29967,
      "department": "MAP",
      "date_type": "completed",
      "title": "mplementasi Kebijakan Penguatan Karakter di SD IT Pelita Khoirul Ummah Bandar Lampung",
      "rev_number": 7,
      "metadata_visibility": "show",
      "status_changed": "2021-05-05 01:03:41",
      "eprint_status": "archive",
      "subjects": [
        "L1"
      ],
      "creators": [
        {
          "name": {
            "given": "Yolanda",
            "honourific": null,
            "family": "Regina",
            "lineage": null
          }
        }
      ],
      "dir": "disk0\/00\/02\/99\/67",
      "date": 2019,
      "type": "thesis",
      "divisions": [
        "FKIP5"
      ],
      "ispublished": "unpub",
      "documents": [
          {
            "language": "en",
            "mime_type": "application\/pdf",
            "eprintid": 29967,
            "security": "public",
            "placement": 1,
            "format": "text",
            "pos": 1,
            "uri": "http:\/\/repository.lppm.unila.ac.id\/id\/document\/134464",
            "rev_number": 1,
            "docid": 134464,
            "main": "23 Yolanda Regina p2.pdf",
            "files": [
                {
                  "uri": "http:\/\/repository.lppm.unila.ac.id\/id\/file\/355205",
                  "objectid": 134464,
                  "filesize": 512049,
                  "datasetid": "document",
                  "hash_type": "MD5",
                  "mtime": "2021-05-04 14:52:47",
                  "filename": "23 Yolanda Regina p2.pdf",
                  "hash": "f91a0bcbc2acaf3d49f16d19f5a8b071",
                  "fileid": 355205,
                  "mime_type": "application\/pdf"
                }
            ]
          }
      ],
      "uri": "http:\/\/repository.lppm.unila.ac.id\/id\/eprint\/29967",
      "full_text_status": "public",
      "thesis_name": "other",
      "userid": 214,
      "lastmod": "2021-05-05 01:03:41",
      "datestamp": "2021-05-05 01:03:41"
    },
    {
      "divisions": [
        "FKIP5"
      ],
      "type": "article",
      "dir": "disk0\/00\/03\/39\/84",
      "date": 2019,
      "creators": [
        {
          "name": {
            "given": "Soleha",
            "lineage": null,
            "family": "Soleha",
            "honourific": null
          }
        },
        {
          "name": {
            "family": "Sowiyah",
            "honourific": null,
            "lineage": null,
            "given": "Sowiyah"
          }
        },
        {
          "name": {
            "given": "supriyadi",
            "family": "supriyadi",
            "honourific": null,
            "lineage": null
          }
        }
      ],
      "publication": "Pedagogi : Jurnal Pendidikan Dasar",
      "datestamp": "2021-09-20 01:07:14",
      "lastmod": "2021-09-20 01:07:14",
      "userid": 968,
      "refereed": "TRUE",
      "full_text_status": "public",
      "uri": "http:\/\/repository.lppm.unila.ac.id\/id\/eprint\/33984",
      "documents": [
          {
            "rev_number": 1,
            "uri": "http:\/\/repository.lppm.unila.ac.id\/id\/document\/154232",
            "format": "text",
            "pos": 1,
            "files": [
                {
                  "datasetid": "document",
                  "filesize": 377181,
                  "fileid": 401457,
                  "mime_type": "application\/pdf",
                  "mtime": "2021-09-19 15:33:40",
                  "hash_type": "MD5",
                  "hash": "f81627cf6d3b29b14b018699a0d945d5",
                  "filename": "4. 18774-43050-1-PB.pdf",
                  "objectid": 154232,
                  "uri": "http:\/\/repository.lppm.unila.ac.id\/id\/file\/401457"
                }
            ],
            "docid": 154232,
            "main": "4. 18774-43050-1-PB.pdf",
            "mime_type": "application\/pdf",
            "language": "en",
            "security": "public",
            "placement": 1,
            "eprintid": 33984
          }
      ],
      "ispublished": "pub",
      "number": 8,
      "date_type": "published",
      "eprintid": 33984,
      "abstract": "The purpose of this study was to find out the positive and significant relationship between pedagogical competencies of the special assistant teacher with the result of learning Indonesian children slow learning in Metro City Inclusive Elementary Schools. This type of research is ex-postfacto correlation. The population is 52 teachers and the research sample is 40 teachers. Data collection tools are questionnaire observation, documentation studies, and interviews. Analysis of he data used is product moment correlation. Based on the research data analysis it can be concluded that there is a positive and significant relationship between pedagogic competencies of the special assistant teacher with the results of learning Indonesian children slow learning.",
      "subjects": [
        "L1"
      ],
      "related_url": [
        {
          "type": "pub",
          "url": "http:\/\/jurnal.fkip.unila.ac.id\/index.php\/pgsd\/article\/view\/18774"
        }
      ],
      "eprint_status": "archive",
      "status_changed": "2021-09-20 01:07:14",
      "metadata_visibility": "show",
      "rev_number": 6,
      "volume": 7,
      "title": "RelationshipCompetencyOf Special Assistant Teacher with slow learner Learning outcomes"
    },
    {
      "thesis_name": "other",
      "uri": "http:\/\/repository.lppm.unila.ac.id\/id\/eprint\/29785",
      "full_text_status": "public",
      "documents": [
          {
            "main": "3 Tesis Gesca Sonarita.pdf",
            "docid": 43988,
            "files": [
                {
                  "fileid": 263569,
                  "mime_type": "application\/pdf",
                  "hash_type": "MD5",
                  "mtime": "2021-04-29 10:26:08",
                  "hash": "8dc861211231015f48ec3ea5612858bf",
                  "filename": "3 Tesis Gesca Sonarita.pdf",
                  "datasetid": "document",
                  "filesize": 413806,
                  "objectid": 43988,
                  "uri": "http:\/\/repository.lppm.unila.ac.id\/id\/file\/263569"
                }
            ],
            "pos": 1,
            "format": "text",
            "uri": "http:\/\/repository.lppm.unila.ac.id\/id\/document\/43988",
            "rev_number": 1,
            "eprintid": 29785,
            "placement": 1,
            "security": "public",
            "language": "en",
            "mime_type": "application\/pdf"
          }
      ],
      "ispublished": "unpub",
      "datestamp": "2021-04-30 01:14:09",
      "lastmod": "2021-04-30 01:14:09",
      "userid": 214,
      "date": 2019,
      "dir": "disk0\/00\/02\/97\/85",
      "creators": [
        {
          "name": {
            "honourific": null,
            "family": "Sonarita",
            "lineage": null,
            "given": "Gesca"
          }
        }
      ],
      "divisions": [
        "FKIP5"
      ],
      "type": "thesis",
      "metadata_visibility": "show",
      "rev_number": 7,
      "title": "Pengaruh Iklim Organisasi, Budaya Organisasi, dan Motivasi Berprestasib terhadap Komitmen Organisasi Pegawai di Institut Teknologi Sumatera Lampung",
      "subjects": [
        "L1"
      ],
      "status_changed": "2021-04-30 01:14:09",
      "eprint_status": "archive",
      "institution": "Universitas Lampung",
      "thesis_type": "masters",
      "date_type": "completed",
      "department": "MAP",
      "eprintid": 29785
    },
    {
      "status_changed": "2021-09-20 01:06:45",
      "eprint_status": "archive",
      "related_url": [
        {
          "type": "pub"
        }
      ],
      "subjects": [
        "L1"
      ],
      "title": "Pengambilan Keputusan dan Analisis Kebijakan Pendidikan",
      "rev_number": 7,
      "metadata_visibility": "show",
      "eprintid": 33975,
      "isbn": "978-623-228-137-0",
      "date_type": "published",
      "userid": 968,
      "lastmod": "2021-09-20 01:06:45",
      "datestamp": "2021-09-20 01:06:45",
      "ispublished": "pub",
      "documents": [
          {
            "mime_type": "application\/pdf",
            "language": "en",
            "security": "public",
            "placement": 1,
            "eprintid": 33975,
            "uri": "http:\/\/repository.lppm.unila.ac.id\/id\/document\/154223",
            "rev_number": 1,
            "format": "text",
            "pos": 1,
            "files": [
                {
                  "objectid": 154223,
                  "uri": "http:\/\/repository.lppm.unila.ac.id\/id\/file\/401400",
                  "mime_type": "application\/pdf",
                  "fileid": 401400,
                  "hash": "3e9771cee504f53b68f51d54a7d43758",
                  "filename": "Buku Pengambilan Keputusan & Analisis Kebijakan.pdf",
                  "mtime": "2021-09-19 13:53:39",
                  "hash_type": "MD5",
                  "datasetid": "document",
                  "filesize": 1136490
                }
            ],
            "main": "Buku Pengambilan Keputusan & Analisis Kebijakan.pdf",
            "docid": 154223
          }
      ],
      "publisher": "Graha Ilmu",
      "full_text_status": "public",
      "uri": "http:\/\/repository.lppm.unila.ac.id\/id\/eprint\/33975",
      "refereed": "TRUE",
      "type": "book",
      "divisions": [
        "FKIP5"
      ],
      "creators": [
        {
          "name": {
            "given": "Sowiyah",
            "lineage": null,
            "honourific": null,
            "family": "Sowiyah"
          }
        }
      ],
      "date": 2019,
      "dir": "disk0\/00\/03\/39\/75",
      "pages": 184
    },
    {
      "refereed": "TRUE",
      "full_text_status": "public",
      "uri": "http:\/\/repository.lppm.unila.ac.id\/id\/eprint\/22854",
      "documents": [
          {
            "mime_type": "application\/pdf",
            "language": "en",
            "eprintid": 22854,
            "placement": 1,
            "security": "public",
            "pos": 1,
            "format": "text",
            "uri": "http:\/\/repository.lppm.unila.ac.id\/id\/document\/36394",
            "rev_number": 2,
            "docid": 36394,
            "main": "Hariri 2019 The role of districts in supporting school leaders’ instructional leadership.pdf",
            "files": [
                {
                  "datasetid": "document",
                  "filesize": 156527,
                  "mime_type": "application\/pdf",
                  "fileid": 209781,
                  "hash": "689bd650d40acfa157cf64fff89680d0",
                  "filename": "Hariri 2019 The role of districts in supporting school leaders’ instructional leadership.pdf",
                  "hash_type": "MD5",
                  "mtime": "2019-10-28 07:29:42",
                  "objectid": 36394,
                  "uri": "http:\/\/repository.lppm.unila.ac.id\/id\/file\/209781"
                }
            ]
          }
      ],
      "publisher": "Emerald Publishing Limited",
      "ispublished": "pub",
      "number": 5,
      "pagerange": "591-600",
      "datestamp": "2020-06-30 03:28:42",
      "lastmod": "2020-06-30 03:28:42",
      "userid": 214,
      "id_number": "10.1108\/JEA-09-2019-227",
      "date": "2019-09-09",
      "dir": "disk0\/00\/02\/28\/54",
      "creators": [
        {
          "name": {
            "given": "Bambang",
            "lineage": null,
            "family": "Sumintono",
            "honourific": null
          },
          "id": "bambang@um.edu.my"
        },
        {
          "id": "hasan.hariri@staff.unila.ac.id",
          "name": {
            "given": "Hasan",
            "lineage": null,
            "family": "Hariri",
            "honourific": null
          }
        },
        {
          "id": "piter@mp.upr.ac.id",
          "name": {
            "family": "Nugroho",
            "honourific": null,
            "lineage": null,
            "given": "Piter Joko"
          }
        },
        {
          "name": {
            "given": "Umi Anugerah",
            "honourific": null,
            "family": "Izzati",
            "lineage": null
          },
          "id": "umianugerah@unesa.ac.id"
        },
        {
          "name": {
            "given": "Joko",
            "honourific": null,
            "family": "Sriyanto",
            "lineage": null
          },
          "id": "joko_sriyanto@uny.ac.id"
        }
      ],
      "issn": "0957-8234",
      "publication": "Journal of Educational Administration",
      "divisions": [
        "FKIP5"
      ],
      "type": "article",
      "metadata_visibility": "show",
      "volume": 57,
      "rev_number": 5,
      "official_url": "https:\/\/www.emerald.com\/insight\/content\/doi\/10.1108\/JEA-09-2019-227\/full\/html",
      "title": "The role of districts in supporting school leaders’ \r\n  instructional leadership:a view and experience from a \r\n  developing country",
      "subjects": [
        "L1"
      ],
      "related_url": [
        {
          "url": "https:\/\/www.emerald.com\/insight\/content\/doi\/10.1108\/JEA-09-2019-227\/full\/html",
          "type": "pub"
        }
      ],
      "succeeds": 14655,
      "eprint_status": "archive",
      "status_changed": "2020-06-30 03:28:42",
      "date_type": "published",
      "eprintid": 22854
    },
    {
      "subjects": [
        "L1"
      ],
      "status_changed": "2020-06-30 03:31:49",
      "eprint_status": "archive",
      "succeeds": 14655,
      "related_url": [
        {
          "url": "https:\/\/www.emerald.com\/insight\/content\/doi\/10.1108\/JEA-09-2019-227\/full\/html",
          "type": "pub"
        }
      ],
      "rev_number": 5,
      "volume": 57,
      "metadata_visibility": "show",
      "official_url": "https:\/\/www.emerald.com\/insight\/content\/doi\/10.1108\/JEA-09-2019-227\/full\/html",
      "title": "The role of districts in supporting school leaders’ \r\n  instructional leadership:a view and experience from a \r\n  developing country",
      "date_type": "published",
      "eprintid": 22873,
      "datestamp": "2020-06-30 03:31:49",
      "pagerange": "591-600",
      "userid": 214,
      "lastmod": "2020-06-30 03:31:49",
      "uri": "http:\/\/repository.lppm.unila.ac.id\/id\/eprint\/22873",
      "full_text_status": "public",
      "refereed": "TRUE",
      "ispublished": "pub",
      "number": 5,
      "documents": [
          {
            "eprintid": 22873,
            "security": "public",
            "placement": 1,
            "language": "en",
            "mime_type": "application\/pdf",
            "main": "Hariri 2019 The role of districts in supporting school leaders’ instructional leadership.pdf",
            "docid": 36418,
            "files": [
                {
                  "uri": "http:\/\/repository.lppm.unila.ac.id\/id\/file\/209920",
                  "objectid": 36418,
                  "filename": "Hariri 2019 The role of districts in supporting school leaders’ instructional leadership.pdf",
                  "hash": "689bd650d40acfa157cf64fff89680d0",
                  "mtime": "2019-10-28 07:29:42",
                  "hash_type": "MD5",
                  "mime_type": "application\/pdf",
                  "fileid": 209920,
                  "filesize": 156527,
                  "datasetid": "document"
                }
            ],
            "format": "text",
            "pos": 1,
            "rev_number": 2,
            "uri": "http:\/\/repository.lppm.unila.ac.id\/id\/document\/36418"
          }
      ],
      "publisher": "Emerald Publishing Limited",
      "divisions": [
        "FKIP5"
      ],
      "type": "article",
      "dir": "disk0\/00\/02\/28\/73",
      "date": "2019-09-09",
      "id_number": "10.1108\/JEA-09-2019-227",
      "publication": "Journal of Educational Administration",
      "issn": "0957-8234",
      "creators": [
        {
          "id": "bambang@um.edu.my",
          "name": {
            "given": "Bambang",
            "honourific": null,
            "family": "Sumintono",
            "lineage": null
          }
        },
        {
          "name": {
            "given": "Hasan",
            "honourific": null,
            "family": "Hariri",
            "lineage": null
          },
          "id": "hasan.hariri@staff.unila.ac.id"
        },
        {
          "id": "piter@mp.upr.ac.id",
          "name": {
            "family": "Nugroho",
            "honourific": null,
            "lineage": null,
            "given": "Piter Joko"
          }
        },
        {
          "id": "umianugerah@unesa.ac.id",
          "name": {
            "given": "Umi Anugerah",
            "honourific": null,
            "family": "Izzati",
            "lineage": null
          }
        },
        {
          "id": "joko_sriyanto@uny.ac.id",
          "name": {
            "lineage": null,
            "family": "Sriyanto",
            "honourific": null,
            "given": "Joko"
          }
        }
      ]
    },
    {
      "type": "thesis",
      "divisions": [
        "FKIP5"
      ],
      "creators": [
        {
          "name": {
            "given": "Suryadi",
            "lineage": null,
            "honourific": null,
            "family": "Suryadi"
          }
        }
      ],
      "date": 2019,
      "dir": "disk0\/00\/02\/99\/64",
      "lastmod": "2021-05-05 01:03:34",
      "userid": 214,
      "datestamp": "2021-05-05 01:03:34",
      "documents": [
          {
            "main": "20 Suryadi p2.pdf",
            "docid": 134453,
            "files": [
                {
                  "objectid": 134453,
                  "uri": "http:\/\/repository.lppm.unila.ac.id\/id\/file\/355175",
                  "datasetid": "document",
                  "filesize": 481571,
                  "fileid": 355175,
                  "mime_type": "application\/pdf",
                  "mtime": "2021-05-04 14:44:21",
                  "hash_type": "MD5",
                  "filename": "20 Suryadi p2.pdf",
                  "hash": "8e6cefd5c92b21d725478d34e3dace07"
                }
            ],
            "pos": 1,
            "format": "text",
            "uri": "http:\/\/repository.lppm.unila.ac.id\/id\/document\/134453",
            "rev_number": 1,
            "eprintid": 29964,
            "placement": 1,
            "security": "public",
            "mime_type": "application\/pdf",
            "language": "en"
          }
      ],
      "ispublished": "unpub",
      "full_text_status": "public",
      "uri": "http:\/\/repository.lppm.unila.ac.id\/id\/eprint\/29964",
      "thesis_name": "other",
      "eprintid": 29964,
      "date_type": "completed",
      "department": "MAP",
      "institution": "Universitas Lampung",
      "thesis_type": "masters",
      "eprint_status": "archive",
      "status_changed": "2021-05-05 01:03:34",
      "subjects": [
        "L1"
      ],
      "title": "Analisis Faktor-Faktor yang Mempengaruhi Gaya Kepemimpinan Kepala Sekolah Berintegrasi di Provinsi Lampung",
      "metadata_visibility": "show",
      "rev_number": 7
    },
    {
      "ispublished": "unpub",
      "documents": [
          {
            "files": [
                {
                  "fileid": 263604,
                  "mime_type": "application\/pdf",
                  "mtime": "2021-04-29 10:39:33",
                  "hash_type": "MD5",
                  "hash": "f4c39825a73c56571d21883aa35cef5d",
                  "filename": "8 Tesis Ria Silvita.pdf",
                  "datasetid": "document",
                  "filesize": 619372,
                  "objectid": 43993,
                  "uri": "http:\/\/repository.lppm.unila.ac.id\/id\/file\/263604"
                }
            ],
            "main": "8 Tesis Ria Silvita.pdf",
            "docid": 43993,
            "uri": "http:\/\/repository.lppm.unila.ac.id\/id\/document\/43993",
            "rev_number": 1,
            "pos": 1,
            "format": "text",
            "placement": 1,
            "security": "public",
            "eprintid": 29790,
            "language": "en",
            "mime_type": "application\/pdf"
          }
      ],
      "full_text_status": "public",
      "uri": "http:\/\/repository.lppm.unila.ac.id\/id\/eprint\/29790",
      "thesis_name": "other",
      "lastmod": "2021-04-30 01:14:20",
      "userid": 214,
      "datestamp": "2021-04-30 01:14:20",
      "creators": [
        {
          "name": {
            "honourific": null,
            "family": "Tanum",
            "lineage": null,
            "given": "Ria Silvita"
          }
        }
      ],
      "date": 2019,
      "dir": "disk0\/00\/02\/97\/90",
      "type": "thesis",
      "divisions": [
        "FKIP5"
      ],
      "title": "Pengaruh Leadership, Customer Focus, dan Process Approach terhadap Kinerja Karyawan Bagian Akademik di Biro Akademik dan Kemahasiswaan Universitas Lampung",
      "rev_number": 7,
      "metadata_visibility": "show",
      "eprint_status": "archive",
      "status_changed": "2021-04-30 01:14:20",
      "subjects": [
        "L1"
      ],
      "thesis_type": "masters",
      "institution": "Universitas Lampung",
      "eprintid": 29790,
      "department": "MAP",
      "date_type": "completed"
    },
    {
      "issn": "2454-6186",
      "creators": [
        {
          "id": "riastusianah@gmail.com",
          "name": {
            "lineage": null,
            "honourific": null,
            "family": "Tusianah",
            "given": "Rias"
          }
        },
        {
          "name": {
            "lineage": null,
            "honourific": null,
            "family": "Suntoro",
            "given": "Irawan"
          },
          "id": "irawan.suntoro@fkip.unila.ac.id"
        },
        {
          "id": "dhkarwan@yahoo.co.id",
          "name": {
            "given": "Dedy H.",
            "honourific": null,
            "family": "Karwan",
            "lineage": null
          }
        }
      ],
      "publication": "International Journal of Research and Innovation in Social Science (IJRISS)",
      "date": "2019-06",
      "dir": "disk0\/00\/02\/29\/81",
      "type": "article",
      "divisions": [
        "FKIP5"
      ],
      "publisher": "www.rsisinternational.org",
      "documents": [
          {
            "files": [
                {
                  "uri": "http:\/\/repository.lppm.unila.ac.id\/id\/file\/210681",
                  "objectid": 36534,
                  "filesize": 675958,
                  "datasetid": "document",
                  "filename": "4 Karwan 2019 Principil Leadership Curriculum Change.pdf",
                  "hash": "fd5aa11fa6e2f6328866685669da9d33",
                  "mtime": "2020-07-01 19:43:58",
                  "hash_type": "MD5",
                  "mime_type": "application\/pdf",
                  "fileid": 210681
                }
            ],
            "docid": 36534,
            "main": "4 Karwan 2019 Principil Leadership Curriculum Change.pdf",
            "rev_number": 2,
            "uri": "http:\/\/repository.lppm.unila.ac.id\/id\/document\/36534",
            "format": "text",
            "pos": 2,
            "security": "public",
            "placement": 2,
            "eprintid": 22981,
            "content": "published",
            "mime_type": "application\/pdf",
            "language": "en"
          }
      ],
      "number": 6,
      "ispublished": "pub",
      "refereed": "TRUE",
      "full_text_status": "public",
      "uri": "http:\/\/repository.lppm.unila.ac.id\/id\/eprint\/22981",
      "lastmod": "2020-07-02 02:15:19",
      "userid": 685,
      "datestamp": "2020-07-02 02:15:19",
      "pagerange": "504-508",
      "eprintid": 22981,
      "title": "Principal’Leadership and Teacher : Curriculum Change",
      "metadata_visibility": "show",
      "volume": 3,
      "rev_number": 9,
      "succeeds": 17206,
      "status_changed": "2020-07-02 02:15:19",
      "eprint_status": "archive",
      "abstract": "The Education growth of a nation depends on the improvement in education. Human development to a great extend on the improvement in Education. The purpose of this study is to investigate  the effect of Curriculum Change  on  Principal’ Leadership and Teacher. A literature review was made in  Google Scholar and DOI . The finding of the researcher  that The Curriculum Change have impact on principals’ leadership and Teacher . Quality of education is a pillar to produce good and reliable human resources, so efforts should always be done continuously improvement  curriculum so that the curriclum change quality of education is better. Therefore, it is necessary to make special policies for improvement.",
      "subjects": [
        "L1"
      ]
    },
    {
      "subjects": [
        "L1"
      ],
      "eprint_status": "archive",
      "status_changed": "2021-05-05 01:03:36",
      "rev_number": 8,
      "metadata_visibility": "show",
      "title": "Pengaruh Keterampilan Manajerial Kepala Sekolah, Disiplin Kerja, dan Motivasi Berprestasi Guru terhadap Kinerja Guru pada SMKN di Bandar Lampung",
      "department": "MAP",
      "date_type": "completed",
      "eprintid": 29965,
      "thesis_type": "masters",
      "institution": "Universitas Lampung",
      "datestamp": "2021-05-05 01:03:36",
      "userid": 214,
      "lastmod": "2021-05-05 01:03:36",
      "thesis_name": "other",
      "uri": "http:\/\/repository.lppm.unila.ac.id\/id\/eprint\/29965",
      "full_text_status": "public",
      "ispublished": "unpub",
      "documents": [
          {
            "security": "public",
            "placement": 1,
            "eprintid": 29965,
            "language": "en",
            "mime_type": "application\/pdf",
            "files": [
                {
                  "objectid": 134454,
                  "uri": "http:\/\/repository.lppm.unila.ac.id\/id\/file\/355182",
                  "datasetid": "document",
                  "filesize": 261313,
                  "fileid": 355182,
                  "mime_type": "application\/pdf",
                  "mtime": "2021-05-04 14:47:04",
                  "hash_type": "MD5",
                  "hash": "ea260610676edb40f7338026654bbe4d",
                  "filename": "21 Titiek Wulandari p2.pdf"
                }
            ],
            "main": "21 Titiek Wulandari p2.pdf",
            "docid": 134454,
            "uri": "http:\/\/repository.lppm.unila.ac.id\/id\/document\/134454",
            "rev_number": 1,
            "format": "text",
            "pos": 1
          }
      ],
      "divisions": [
        "FKIP5"
      ],
      "type": "thesis",
      "date": 2019,
      "dir": "disk0\/00\/02\/99\/65",
      "creators": [
        {
          "name": {
            "family": "Wulandari",
            "honourific": null,
            "lineage": null,
            "given": "Titiek"
          }
        }
      ]
    },
    {
      "date": "2019-09-09",
      "dir": "disk0\/00\/02\/88\/21",
      "creators": [
        {
          "id": null,
          "name": {
            "lineage": null,
            "family": "piter",
            "honourific": null,
            "given": "Joko N"
          }
        },
        {
          "name": {
            "family": "Bambang",
            "honourific": null,
            "lineage": null,
            "given": "Sumitro"
          },
          "id": null
        },
        {
          "id": "hasan.hariri@staff.unila.ac.id",
          "name": {
            "given": "Hasan",
            "family": "Hariri",
            "honourific": null,
            "lineage": null
          }
        },
        {
          "name": {
            "given": "Sriyanto",
            "lineage": null,
            "family": "Joko",
            "honourific": null
          },
          "id": null
        }
      ],
      "divisions": [
        "FKIP5"
      ],
      "type": "other",
      "uri": "http:\/\/repository.lppm.unila.ac.id\/id\/eprint\/28821",
      "full_text_status": "public",
      "documents": [
          {
            "pos": 1,
            "format": "text",
            "rev_number": 1,
            "uri": "http:\/\/repository.lppm.unila.ac.id\/id\/document\/42914",
            "main": "The role of districts in supporting school leaders instructional leadership a view and experience from a developing.pdf",
            "docid": 42914,
            "files": [
                {
                  "datasetid": "document",
                  "filesize": 2849541,
                  "fileid": 255768,
                  "mime_type": "application\/pdf",
                  "mtime": "2021-04-01 05:32:51",
                  "hash_type": "MD5",
                  "filename": "The role of districts in supporting school leaders instructional leadership a view and experience from a developing.pdf",
                  "hash": "be1e040924537cf2fd9400286372a6d6",
                  "objectid": 42914,
                  "uri": "http:\/\/repository.lppm.unila.ac.id\/id\/file\/255768"
                }
            ],
            "language": "en",
            "mime_type": "application\/pdf",
            "eprintid": 28821,
            "placement": 1,
            "security": "public"
          }
      ],
      "publisher": "Emerald Publishing Limited",
      "ispublished": "pub",
      "datestamp": "2021-04-05 04:48:51",
      "lastmod": "2021-04-05 04:48:51",
      "userid": 214,
      "eprintid": 28821,
      "metadata_visibility": "show",
      "rev_number": 9,
      "title": "The role of districts in supporting school leaders’ instructional leadership: a view and experience from a developing country.",
      "subjects": [
        "L1",
        "LB1501",
        "LC5201"
      ],
      "eprint_status": "archive",
      "status_changed": "2021-04-05 04:48:51"
    }
]

