[
    {
      "divisions": [
        "FP20"
      ],
      "type": "article",
      "date": "2011-11-29",
      "dir": "disk0\/00\/04\/22\/28",
      "creators": [
        {
          "name": {
            "given": "Rara",
            "honourific": null,
            "family": "Diantari",
            "lineage": null
          },
          "id": "rara.diantari@fp.unila.ac.id"
        }
      ],
      "issn": "978-979-8510-34-2",
      "publication": "Prosiding Seminar Nasional Sains dan Teknologi IV",
      "pagerange": "457-468",
      "datestamp": "2022-06-09 01:06:27",
      "userid": 218,
      "lastmod": "2022-06-09 01:06:27",
      "refereed": "TRUE",
      "full_text_status": "public",
      "uri": "http:\/\/repository.lppm.unila.ac.id\/id\/eprint\/42228",
      "publisher": "LEMBAGA PENELITIAN UNIVERSITAS LAMPUNG",
      "documents": [
          {
            "language": "en",
            "mime_type": "application\/pdf",
            "eprintid": 42228,
            "security": "public",
            "placement": 1,
            "format": "text",
            "pos": 1,
            "rev_number": 1,
            "uri": "http:\/\/repository.lppm.unila.ac.id\/id\/document\/163918",
            "main": "effect of eutrofikasi_makalah.pdf",
            "docid": 163918,
            "files": [
                {
                  "fileid": 464967,
                  "mime_type": "application\/pdf",
                  "hash_type": "MD5",
                  "mtime": "2022-06-08 19:39:46",
                  "hash": "d3cf3773d88c42de716cdf7fcc24c313",
                  "filename": "effect of eutrofikasi_makalah.pdf",
                  "datasetid": "document",
                  "filesize": 3159636,
                  "objectid": 163918,
                  "uri": "http:\/\/repository.lppm.unila.ac.id\/id\/file\/464967"
                }
            ]
          }
      ],
      "ispublished": "pub",
      "date_type": "published",
      "eprintid": 42228,
      "abstract": "Ikan haplochromine cichlida adalah spesies asli Danau Victoria. Sebelum tahun 1980-an, haplochromine ciclids mendominasi Danau Victoria, baik dalam ukuran biomassa atau jumlah spesies. Sejak awal tahun 1980 biomasa dan spesies\r\nhaplochromine menurun drastis. Namun beberapa penelitian yang dilakukan sekitar tahun 1990 menunjukkan terjadi peningkatan jumlah beberapa spesies haplochromine dan juga perubahan diet. Bersamaan dengan adanya perubahan ekologis dari haplochromine proses eutrofikasi juga terjadi. Eutrofikasi memiliki peran sangat besar dalam merubah ketersediaan jenis dan jumlah pakan di Danau Victoria. Penelitian ini dilakukan untuk menganalisa hubungan antara kondisi yang berbeda dari suatu daerah dengan diet haplochromine. Dalam penelitian ini dikumpulkan data kebiasaan pakan dari 50 ikan yang diambil dari 6 stasiun yang berbeda di Teluk Mwanza Danau Victoria dan juga data kualitas air dari masing stasiun pengamatan. Untuk mengetahui hubungan antara lingkungan dengan diet ikan dilakukan uji non-parametrik kruskal wallis dilanjutkan dengan uji Pairwise Man-Whitney. Hasil penelitian menunjukan bahwa eutrofikasi tidak berpengaruh secara signifikan terhadap diet ikan.",
      "subjects": [
        "SH"
      ],
      "eprint_status": "archive",
      "status_changed": "2022-06-09 01:06:27",
      "metadata_visibility": "show",
      "rev_number": 6,
      "title": "PENGARUH EUTROFIKASI TERHADAP DIET IKAN\r\nHAPLOCHROMINE CICHLIDS DI TELUK MWANZA DANAU\r\nVICTORIA"
    },
    {
      "eprintid": 417,
      "date_type": "published",
      "eprint_status": "archive",
      "status_changed": "2016-08-28 13:14:00",
      "abstract": "Kajian potensi dan pemanfaatan cumi-cumi (Loligo spp) di perairan laut Provinsi Lampung dilakukan berdasarkan analisis terhadap data hasil tangkapan dan trip penangkapan cumi-cumi selama kurun waktu 2004-2008.  Analisis catch per unit effort (CPUE) digunakan untuk\r\nmenduga potensi lestari (MSY) cumi-cumi dan upaya penangkapan yang optimum.  Analisis juga dilakukan untuk mengetahui keadaan musim penangkapan berdasarkan data kuartalan. Nilai MSY dan upaya penangkapan cumi-cumi di Provinsi Lampung masing-masing adalah 4.024,312 ton dan 573.713 trip. Musim penangkapan cumi-cumi tertinggi terjadi pada kuartal I,yaitu pada bulan Januari-Maret dan semakin menurun hingga kuartal III (Juli-September). \r\nDiketahui bahwa status perikanan cumi-cumi pada tahun 2008 telah menunjukkan overfishing,sehingga diperlukan upaya pengaturan.  Pengaturan lebih ditujukan pada pembatasan hasil tangkapan dan bukan upaya penangkapan-nya, yaitu sekitar 80% dari potensi lestarinya. Alat tangkap yang perlu dibatasi hasil tangkapannya adalah purse seine, jaring insang hanyut, jaring insang tetap, dan bagan perahu.",
      "subjects": [
        "SH"
      ],
      "official_url": "http:\/\/perpustakaan.kkp.go.id\/",
      "title": "Kajian potensi dan pemanfaatan sumberdaya cumi-cumi (Loligo spp) dan upaya pengelolaannya di perairan pesisir Lampung",
      "metadata_visibility": "show",
      "volume": 5,
      "rev_number": 6,
      "type": "article",
      "divisions": [
        "FP20"
      ],
      "creators": [
        {
          "id": "indra.yudha@fp.unila.ac.id",
          "name": {
            "given": "Indra",
            "lineage": null,
            "honourific": null,
            "family": "Gumay Yudha"
          }
        }
      ],
      "issn": "0216-4841",
      "publication": "Jurnal Mitra Bahari",
      "date": "2011-01",
      "dir": "disk0\/00\/00\/04\/17",
      "lastmod": "2016-08-28 13:14:00",
      "userid": 509,
      "pagerange": "25-45",
      "datestamp": "2016-08-28 13:14:00",
      "documents": [
          {
            "files": [
                {
                  "objectid": 376,
                  "uri": "http:\/\/repository.lppm.unila.ac.id\/id\/file\/2302",
                  "mime_type": "application\/pdf",
                  "fileid": 2302,
                  "filename": "jurnal mitra bahari vol 5 no 1 thn 2011 IGY.pdf",
                  "hash": "9844b8e2af639c5d55dec0fd122992ef",
                  "hash_type": "MD5",
                  "mtime": "2016-08-27 04:36:47",
                  "datasetid": "document",
                  "filesize": 4565151
                }
            ],
            "main": "jurnal mitra bahari vol 5 no 1 thn 2011 IGY.pdf",
            "docid": 376,
            "rev_number": 1,
            "uri": "http:\/\/repository.lppm.unila.ac.id\/id\/document\/376",
            "format": "text",
            "pos": 1,
            "security": "public",
            "placement": 1,
            "eprintid": 417,
            "mime_type": "application\/pdf",
            "language": "en"
          }
      ],
      "publisher": "Kementerian Kelautan dan Perikanan RI",
      "number": 1,
      "ispublished": "pub",
      "contributors": [
        {
          "type": "http:\/\/www.loc.gov\/loc.terms\/relators\/AUT"
        }
      ],
      "refereed": "TRUE",
      "full_text_status": "public",
      "uri": "http:\/\/repository.lppm.unila.ac.id\/id\/eprint\/417"
    },
    {
      "full_text_status": "public",
      "uri": "http:\/\/repository.lppm.unila.ac.id\/id\/eprint\/420",
      "refereed": "TRUE",
      "ispublished": "pub",
      "contributors": [
        {
          "type": "http:\/\/www.loc.gov\/loc.terms\/relators\/AUT"
        }
      ],
      "publisher": "Lembaga Penelitian Universitas Lampung",
      "documents": [
          {
            "mime_type": "application\/pdf",
            "language": "en",
            "eprintid": 420,
            "security": "public",
            "placement": 1,
            "format": "text",
            "pos": 1,
            "uri": "http:\/\/repository.lppm.unila.ac.id\/id\/document\/379",
            "rev_number": 1,
            "main": "IGY 2011 Prosiding Seminar Dies Unila 2011.pdf",
            "docid": 379,
            "files": [
                {
                  "datasetid": "document",
                  "filesize": 978610,
                  "fileid": 2322,
                  "mime_type": "application\/pdf",
                  "mtime": "2016-08-27 15:37:08",
                  "hash_type": "MD5",
                  "filename": "IGY 2011 Prosiding Seminar Dies Unila 2011.pdf",
                  "hash": "01ac1abe4042b3d8e9ecd26e04ac4b2c",
                  "objectid": 379,
                  "uri": "http:\/\/repository.lppm.unila.ac.id\/id\/file\/2322"
                }
            ]
          }
      ],
      "pagerange": "I-01-I-11",
      "datestamp": "2016-08-28 13:15:06",
      "lastmod": "2016-08-28 13:15:06",
      "userid": 509,
      "dir": "disk0\/00\/00\/04\/20",
      "date": "2011-10",
      "publication": "Prosiding Seminar Hasil-Hasil Penelitian dan Pengabdian kepada Masyarakat Universitas Lampung 2011",
      "issn": "ISBN 978-979-8510-22-9",
      "creators": [
        {
          "name": {
            "family": "Gumay Yudha",
            "honourific": null,
            "lineage": null,
            "given": "Indra"
          },
          "id": "indra.yudha@fp.unila.ac.id"
        }
      ],
      "divisions": [
        "FP20"
      ],
      "type": "article",
      "rev_number": 6,
      "metadata_visibility": "show",
      "title": "Keanekaragaman jenis dan karakteristik ikan-ikan di perairan Way Tulang Bawang, Kabupaten Tulang Bawang",
      "subjects": [
        "SH"
      ],
      "abstract": "Penelitian ini dilakukan pada Oktober-November 2009 di Kecamatan Menggala, Kabupaten Tulang\r\nBawang, Lampung.  Tujuan penelitian ini adalah untuk mengkaji komposisi jenis dan\r\nkarakteristik ikan-ikan yang tertangkap di perairan Way Tulang Bawang.  Metode penelitian yang\r\ndigunakan adalah metode survei dengan mengumpulkan ikan-ikan yang tertangkap oleh nelayan\r\nsetempat untuk selanjutnya dianalisis di laboratorium.  Identifikasi ikan dilakukan berdasarkan Kottelat et.al.  (2003).  Berdasarkan hasil penelitian diketahui bahwa jenis-jenis ikan yang dominan di Way Tulang Bawang adalah ikan-ikan famili Cyprinidae dengan komposisi 91,98%.\r\nIkan-ikan tersebut sebagian besar merupakan herbivora. Ikan-ikan yang dominan adalah wader (Osteochilus  enneaporus), ikan palau (Osteochilus hasseltii), ikan lampan (Barbodes gonionotus), dan ikan ulubatu (Barbichthys laevis).",
      "eprint_status": "archive",
      "status_changed": "2016-08-28 13:15:06",
      "date_type": "published",
      "eprintid": 420
    }
]

